COAL/processor/processor.v
`timescale 1ns/1ps

// Simple single-cycle RISC-V processor.
// Supported instructions:
// R-type: add, sub, and, or
// I-type: addi, lw
// S-type: sw
// B-type: beq

module processor(
    input clk,
    input reset
);
    reg [31:0] pc;
    reg [31:0] instr_mem [0:63];
    reg [31:0] data_mem  [0:63];
    reg [31:0] regs      [0:31];

    wire [31:0] instruction;
    wire [6:0] opcode;
    wire [4:0] rd;
    wire [2:0] funct3;
    wire [4:0] rs1;
    wire [4:0] rs2;
    wire [6:0] funct7;

    wire branch;
    wire mem_read;
    wire mem_to_reg;
    wire [1:0] alu_op;
    wire mem_write;
    wire alu_src;
    wire reg_write;

    wire [31:0] read_data1;
    wire [31:0] read_data2;
    wire [31:0] imm;
    wire [3:0] alu_control_signal;
    wire [31:0] alu_input2;
    wire [31:0] alu_result;
    wire zero;
    wire [31:0] mem_read_data;
    wire [31:0] write_data;

    wire [31:0] pc_plus_4;
    wire [31:0] branch_target;
    wire pc_src;
    wire [31:0] next_pc;

    integer i;

    assign instruction = instr_mem[pc[7:2]];

    assign opcode = instruction[6:0];
    assign rd     = instruction[11:7];
    assign funct3 = instruction[14:12];
    assign rs1    = instruction[19:15];
    assign rs2    = instruction[24:20];
    assign funct7 = instruction[31:25];

    control_unit control(
        .opcode(opcode),
        .branch(branch),
        .mem_read(mem_read),
        .mem_to_reg(mem_to_reg),
        .alu_op(alu_op),
        .mem_write(mem_write),
        .alu_src(alu_src),
        .reg_write(reg_write)
    );

    imm_gen immediate_generator(
        .instruction(instruction),
        .imm(imm)
    );

    alu_control alu_ctrl(
        .alu_op(alu_op),
        .funct3(funct3),
        .funct7(funct7),
        .alu_control_signal(alu_control_signal)
    );

    assign read_data1 = (rs1 == 0) ? 32'b0 : regs[rs1];
    assign read_data2 = (rs2 == 0) ? 32'b0 : regs[rs2];

    assign alu_input2 = alu_src ? imm : read_data2;

    alu main_alu(
        .a(read_data1),
        .b(alu_input2),
        .alu_control_signal(alu_control_signal),
        .result(alu_result),
        .zero(zero)
    );

    assign mem_read_data = data_mem[alu_result[7:2]];
    assign write_data = mem_to_reg ? mem_read_data : alu_result;

    assign pc_plus_4 = pc + 4;
    assign branch_target = pc + imm;
    assign pc_src = branch & zero;
    assign next_pc = pc_src ? branch_target : pc_plus_4;

    always @(posedge clk or posedge reset) begin
        if (reset) begin
            pc <= 0;
            for (i = 0; i < 32; i = i + 1)
                regs[i] <= 0;
            for (i = 0; i < 64; i = i + 1)
                data_mem[i] <= 0;
        end else begin
            pc <= next_pc;

            if (mem_write)
                data_mem[alu_result[7:2]] <= read_data2;

            if (reg_write && rd != 0)
                regs[rd] <= write_data;
        end
    end
endmodule

module control_unit(
    input [6:0] opcode,
    output reg branch,
    output reg mem_read,
    output reg mem_to_reg,
    output reg [1:0] alu_op,
    output reg mem_write,
    output reg alu_src,
    output reg reg_write
);
    always @(*) begin
        branch = 0;
        mem_read = 0;
        mem_to_reg = 0;
        alu_op = 2'b00;
        mem_write = 0;
        alu_src = 0;
        reg_write = 0;

        case (opcode)
            7'b0110011: begin // R-type
                alu_op = 2'b10;
                reg_write = 1;
            end
            7'b0010011: begin // addi
                alu_op = 2'b00;
                alu_src = 1;
                reg_write = 1;
            end
            7'b0000011: begin // lw
                mem_read = 1;
                mem_to_reg = 1;
                alu_src = 1;
                reg_write = 1;
            end
            7'b0100011: begin // sw
                alu_src = 1;
                mem_write = 1;
            end
            7'b1100011: begin // beq
                branch = 1;
                alu_op = 2'b01;
            end
        endcase
    end
endmodule

module imm_gen(
    input [31:0] instruction,
    output reg [31:0] imm
);
    wire [6:0] opcode;
    assign opcode = instruction[6:0];

    always @(*) begin
        case (opcode)
            7'b0010011,
            7'b0000011:
                imm = {{20{instruction[31]}}, instruction[31:20]};

            7'b0100011:
                imm = {{20{instruction[31]}}, instruction[31:25], instruction[11:7]};

            7'b1100011:
                imm = {{19{instruction[31]}}, instruction[31], instruction[7],
                       instruction[30:25], instruction[11:8], 1'b0};

            default:
                imm = 32'b0;
        endcase
    end
endmodule

module alu_control(
    input [1:0] alu_op,
    input [2:0] funct3,
    input [6:0] funct7,
    output reg [3:0] alu_control_signal
);
    always @(*) begin
        case (alu_op)
            2'b00:
                alu_control_signal = 4'b0010; // add for lw, sw, addi
            2'b01:
                alu_control_signal = 4'b0110; // subtract for beq
            2'b10: begin
                case ({funct7, funct3})
                    10'b0000000_000: alu_control_signal = 4'b0010; // add
                    10'b0100000_000: alu_control_signal = 4'b0110; // sub
                    10'b0000000_111: alu_control_signal = 4'b0000; // and
                    10'b0000000_110: alu_control_signal = 4'b0001; // or
                    default:         alu_control_signal = 4'b0010;
                endcase
            end
            default:
                alu_control_signal = 4'b0010;
        endcase
    end
endmodule

module alu(
    input [31:0] a,
    input [31:0] b,
    input [3:0] alu_control_signal,
    output reg [31:0] result,
    output zero
);
    always @(*) begin
        case (alu_control_signal)
            4'b0000: result = a & b;
            4'b0001: result = a | b;
            4'b0010: result = a + b;
            4'b0110: result = a - b;
            default: result = 0;
        endcase
    end

    assign zero = (result == 0);
endmodule

COAL/processor/processor_tb.v
`timescale 1ns/1ps

module processor_tb;
    reg clk;
    reg reset;

    processor uut(
        .clk(clk),
        .reset(reset)
    );

    always #5 clk = ~clk;

    initial begin
        $dumpfile("processor_tb.vcd");
        $dumpvars(0, processor_tb);

        clk = 0;
        reset = 1;

        // Program:
        // x1 = 5
        // x2 = 10
        // x3 = x1 + x2 = 15
        // memory[0] = x3
        // x4 = memory[0] = 15
        // if x4 == x3, skip next instruction
        // x5 = 99  (should be skipped)
        // x6 = 7
        uut.instr_mem[0] = 32'h00500093; // addi x1, x0, 5
        uut.instr_mem[1] = 32'h00A00113; // addi x2, x0, 10
        uut.instr_mem[2] = 32'h002081B3; // add  x3, x1, x2
        uut.instr_mem[3] = 32'h00302023; // sw   x3, 0(x0)
        uut.instr_mem[4] = 32'h00002203; // lw   x4, 0(x0)
        uut.instr_mem[5] = 32'h00320463; // beq  x4, x3, 8
        uut.instr_mem[6] = 32'h06300293; // addi x5, x0, 99
        uut.instr_mem[7] = 32'h00700313; // addi x6, x0, 7

        #12;
        reset = 0;

        #100;

        $display("x1 = %0d", uut.regs[1]);
        $display("x2 = %0d", uut.regs[2]);
        $display("x3 = %0d", uut.regs[3]);
        $display("x4 = %0d", uut.regs[4]);
        $display("x5 = %0d", uut.regs[5]);
        $display("x6 = %0d", uut.regs[6]);
        $display("memory[0] = %0d", uut.data_mem[0]);

        if (uut.regs[3] == 15 &&
            uut.regs[4] == 15 &&
            uut.regs[5] == 0 &&
            uut.regs[6] == 7 &&
            uut.data_mem[0] == 15)
            $display("TEST PASSED");
        else
            $display("TEST FAILED");

        $finish;
    end
endmodule

COAL/processor/processor_tb.vcd
$date
	Thu Apr 23 15:43:40 2026
$end
$version
	Icarus Verilog
$end
$timescale
	1ps
$end
$scope module processor_tb $end
$var reg 1 ! clk $end
$var reg 1 " reset $end
$scope module uut $end
$var wire 1 ! clk $end
$var wire 32 # instruction [31:0] $end
$var wire 32 $ mem_read_data [31:0] $end
$var wire 1 % pc_src $end
$var wire 1 " reset $end
$var wire 1 & zero $end
$var wire 32 ' write_data [31:0] $end
$var wire 5 ( rs2 [4:0] $end
$var wire 5 ) rs1 [4:0] $end
$var wire 1 * reg_write $end
$var wire 32 + read_data2 [31:0] $end
$var wire 32 , read_data1 [31:0] $end
$var wire 5 - rd [4:0] $end
$var wire 32 . pc_plus_4 [31:0] $end
$var wire 7 / opcode [6:0] $end
$var wire 32 0 next_pc [31:0] $end
$var wire 1 1 mem_write $end
$var wire 1 2 mem_to_reg $end
$var wire 1 3 mem_read $end
$var wire 32 4 imm [31:0] $end
$var wire 7 5 funct7 [6:0] $end
$var wire 3 6 funct3 [2:0] $end
$var wire 32 7 branch_target [31:0] $end
$var wire 1 8 branch $end
$var wire 1 9 alu_src $end
$var wire 32 : alu_result [31:0] $end
$var wire 2 ; alu_op [1:0] $end
$var wire 32 < alu_input2 [31:0] $end
$var wire 4 = alu_control_signal [3:0] $end
$var reg 32 > pc [31:0] $end
$var integer 32 ? i [31:0] $end
$scope module alu_ctrl $end
$var wire 3 @ funct3 [2:0] $end
$var wire 7 A funct7 [6:0] $end
$var wire 2 B alu_op [1:0] $end
$var reg 4 C alu_control_signal [3:0] $end
$upscope $end
$scope module control $end
$var wire 7 D opcode [6:0] $end
$var reg 2 E alu_op [1:0] $end
$var reg 1 9 alu_src $end
$var reg 1 8 branch $end
$var reg 1 3 mem_read $end
$var reg 1 2 mem_to_reg $end
$var reg 1 1 mem_write $end
$var reg 1 * reg_write $end
$upscope $end
$scope module immediate_generator $end
$var wire 32 F instruction [31:0] $end
$var wire 7 G opcode [6:0] $end
$var reg 32 H imm [31:0] $end
$upscope $end
$scope module main_alu $end
$var wire 32 I a [31:0] $end
$var wire 4 J alu_control_signal [3:0] $end
$var wire 32 K b [31:0] $end
$var wire 1 & zero $end
$var reg 32 L result [31:0] $end
$upscope $end
$upscope $end
$upscope $end
$enddefinitions $end
$comment Show the parameter values. $end
$dumpall
$end
#0
$dumpvars
b101 L
b101 K
b10 J
b0 I
b101 H
b10011 G
b10100000000000010010011 F
b0 E
b10011 D
b10 C
b0 B
b0 A
b0 @
b1000000 ?
b0 >
b10 =
b101 <
b0 ;
b101 :
19
08
b101 7
b0 6
b0 5
b101 4
03
02
01
b100 0
b10011 /
b100 .
b1 -
b0 ,
b0 +
1*
b0 )
b101 (
b101 '
0&
0%
b0 $
b10100000000000010010011 #
1"
0!
$end
#5000
b1000000 ?
1!
#10000
0!
#12000
0"
#15000
b1010 '
b1010 :
b1010 L
b1010 <
b1010 K
b10 -
b1010 (
b1010 4
b1010 H
b101000000000000100010011 #
b101000000000000100010011 F
b1000 0
b1000 .
b1110 7
b100 >
1!
#20000
0!
#25000
b1111 '
b1111 :
b1111 L
b10 ;
b10 B
b10 E
1*
09
b101 ,
b101 I
b1010 +
b1010 <
b1010 K
b110011 /
b110011 D
b11 -
b1 )
b10 (
b0 4
b0 H
b110011 G
b1000001000000110110011 #
b1000001000000110110011 F
b1100 0
b1100 .
b1000 7
b1000 >
1!
#30000
0!
#35000
b0 '
1&
b0 :
b0 L
b0 <
b0 K
11
19
0*
b0 ;
b0 B
b0 E
b0 ,
b0 I
b1111 +
b100011 /
b100011 D
b0 -
b10 6
b10 @
b0 )
b11 (
b100011 G
b1100000010000000100011 #
b1100000010000000100011 F
b10000 0
b10000 .
b1100 7
b1100 >
1!
#40000
0!
#45000
b1111 '
1*
12
13
19
01
b0 +
b11 /
b11 D
b100 -
b0 (
b11 G
b10001000000011 #
b10001000000011 F
b10100 0
b1111 $
b10100 .
b10000 7
b10000 >
1!
#50000
0!
#55000
1%
b1111 $
b110 =
b110 C
b110 J
b0 '
1&
b0 :
b0 L
b1 ;
b1 B
b1 E
18
0*
09
02
03
b1111 ,
b1111 I
b1111 +
b1111 <
b1111 K
b1100011 /
b1100011 D
b1000 -
b0 6
b0 @
b100 )
b11 (
b1000 4
b1000 H
b1100011 G
b1100100000010001100011 #
b1100100000010001100011 F
b11100 0
b11000 .
b11100 7
b10100 >
1!
#60000
0!
#65000
b111 '
b0 $
b10 =
b10 C
b10 J
0%
0&
b111 :
b111 L
b111 <
b111 K
1*
19
b0 ;
b0 B
b0 E
08
b0 ,
b0 I
b0 +
b10011 /
b10011 D
b110 -
b0 )
b111 (
b111 4
b111 H
b10011 G
b11100000000001100010011 #
b11100000000001100010011 F
b100000 0
b100000 .
b100011 7
b11100 >
1!
#70000
0!
#75000
bx '
bx $
x&
bx :
bx L
0*
09
bx ,
bx I
bx +
bx <
bx K
bx /
bx D
bx -
bx 6
bx @
bx )
bx (
bx 5
bx A
b0 4
b0 H
bx G
bx #
bx F
b100100 0
b100100 .
b100000 7
b100000 >
1!
#80000
0!
#85000
b101000 0
b101000 .
b100100 7
b100100 >
1!
#90000
0!
#95000
b101100 0
b101100 .
b101000 7
b101000 >
1!
#100000
0!
#105000
b110000 0
b110000 .
b101100 7
b101100 >
1!
